AUTHORS
LICENSE
MANIFEST.in
README.rst
setup.py
django_rest_auth_knaperek.egg-info/PKG-INFO
django_rest_auth_knaperek.egg-info/SOURCES.txt
django_rest_auth_knaperek.egg-info/dependency_links.txt
django_rest_auth_knaperek.egg-info/not-zip-safe
django_rest_auth_knaperek.egg-info/requires.txt
django_rest_auth_knaperek.egg-info/top_level.txt
rest_auth/__init__.py
rest_auth/admin.py
rest_auth/app_settings.py
rest_auth/models.py
rest_auth/serializers.py
rest_auth/social_serializers.py
rest_auth/urls.py
rest_auth/utils.py
rest_auth/views.py
rest_auth/registration/__init__.py
rest_auth/registration/app_settings.py
rest_auth/registration/serializers.py
rest_auth/registration/urls.py
rest_auth/registration/views.py
rest_auth/tests/__init__.py
rest_auth/tests/django_urls.py
rest_auth/tests/settings.py
rest_auth/tests/test_api.py
rest_auth/tests/test_base.py
rest_auth/tests/test_social.py
rest_auth/tests/urls.py