Metadata-Version: 1.1
Name: django-rest-auth-knaperek
Version: 0.8.2
Summary: Create a set of REST API endpoints for Authentication and Registration. TEMPORARY BUGFIX RELEASE.
Home-page: http://github.com/Tivix/django-rest-auth
Author: Sumit Chachra
Author-email: chachra@tivix.com
License: UNKNOWN
Keywords: django rest auth registration rest-framework django-registration api
Platform: UNKNOWN
Classifier: Framework :: Django
Classifier: Intended Audience :: Developers
Classifier: Intended Audience :: System Administrators
Classifier: Operating System :: OS Independent
Classifier: Topic :: Software Development
